rsylla-0.1.0.dist-info/METADATA
rsylla-0.1.0.dist-info/WHEEL
rsylla-0.1.0.dist-info/licenses/LICENSE
rsylla/__init__.py
rsylla/__init__.pyi
rsylla/_rsylla.abi3.so
rsylla/py.typed
rsylla-0.1.0.dist-info/RECORD
