Metadata-Version: 2.4
Name: rsylla
Version: 0.1.0
Classifier: Programming Language :: Rust
Classifier: Programming Language :: Python :: Implementation :: CPython
Classifier: Programming Language :: Python :: Implementation :: PyPy
Classifier: Programming Language :: Python :: 3
Classifier: Programming Language :: Python :: 3.11
Classifier: Programming Language :: Python :: 3.12
Classifier: Programming Language :: Python :: 3.13
License-File: LICENSE
Summary: Python bindings for ScyllaDB/Cassandra using scylla-rust-driver
Keywords: scylla,scylladb,cassandra,database
License: MIT OR Apache-2.0
Requires-Python: >=3.11
